[
  {"symbol": "SPX",   "description": "S&P 500 Index",                    "type": "Index"},
  {"symbol": "SPXW",  "description": "S&P 500 Weekly Index",             "type": "Index"},
  {"symbol": "NDX",   "description": "NASDAQ-100 Index",                 "type": "Index"},
  {"symbol": "NQX",   "description": "NASDAQ-100 Reduced Value Index",   "type": "Index"},
  {"symbol": "RUT",   "description": "Russell 2000 Index",               "type": "Index"},
  {"symbol": "RUA",   "description": "Russell 3000 Index",               "type": "Index"},
  {"symbol": "VIX",   "description": "CBOE Volatility Index",            "type": "Index"},
  {"symbol": "VIX9D", "description": "CBOE VIX 9-Day",                   "type": "Index"},
  {"symbol": "DJX",   "description": "Dow Jones Index (1/100)",          "type": "Index"},
  {"symbol": "XSP",   "description": "Mini-SPX Index",                   "type": "Index"},
  {"symbol": "MXEA",  "description": "MSCI EAFE Index",                  "type": "Index"},
  {"symbol": "MXEF",  "description": "MSCI Emerging Markets Index",      "type": "Index"},
  {"symbol": "OEX",   "description": "S&P 100 Index",                    "type": "Index"},
  {"symbol": "XEO",   "description": "S&P 100 European-Style Index",     "type": "Index"},
  {"symbol": "DJI",   "description": "Dow Jones Industrial Average",     "type": "Index"},
  {"symbol": "COMP",  "description": "NASDAQ Composite Index",           "type": "Index"},
  {"symbol": "SPY",   "description": "SPDR S&P 500 ETF",                 "type": "ETF"},
  {"symbol": "IVV",   "description": "iShares Core S&P 500 ETF",        "type": "ETF"},
  {"symbol": "VOO",   "description": "Vanguard S&P 500 ETF",             "type": "ETF"},
  {"symbol": "QQQ",   "description": "Invesco NASDAQ-100 ETF",           "type": "ETF"},
  {"symbol": "IWM",   "description": "iShares Russell 2000 ETF",        "type": "ETF"},
  {"symbol": "DIA",   "description": "SPDR Dow Jones Industrial ETF",   "type": "ETF"},
  {"symbol": "VTI",   "description": "Vanguard Total Stock Market ETF",  "type": "ETF"},
  {"symbol": "ITOT",  "description": "iShares Core S&P Total US Mkt",   "type": "ETF"},
  {"symbol": "SCHB",  "description": "Schwab US Broad Market ETF",       "type": "ETF"},
  {"symbol": "MDY",   "description": "SPDR S&P MidCap 400 ETF",         "type": "ETF"},
  {"symbol": "IJH",   "description": "iShares Core S&P Mid-Cap ETF",    "type": "ETF"},
  {"symbol": "IJR",   "description": "iShares Core S&P Small-Cap ETF",  "type": "ETF"},
  {"symbol": "VXF",   "description": "Vanguard Extended Market ETF",     "type": "ETF"},
  {"symbol": "XLE",   "description": "Energy Select SPDR ETF",           "type": "ETF"},
  {"symbol": "XLF",   "description": "Financial Select SPDR ETF",        "type": "ETF"},
  {"symbol": "XLK",   "description": "Technology Select SPDR ETF",       "type": "ETF"},
  {"symbol": "XLV",   "description": "Health Care Select SPDR ETF",      "type": "ETF"},
  {"symbol": "XLI",   "description": "Industrial Select SPDR ETF",       "type": "ETF"},
  {"symbol": "XLY",   "description": "Consumer Discret. Select SPDR ETF","type": "ETF"},
  {"symbol": "XLP",   "description": "Consumer Staples Select SPDR ETF", "type": "ETF"},
  {"symbol": "XLB",   "description": "Materials Select SPDR ETF",        "type": "ETF"},
  {"symbol": "XLRE",  "description": "Real Estate Select SPDR ETF",      "type": "ETF"},
  {"symbol": "XLU",   "description": "Utilities Select SPDR ETF",        "type": "ETF"},
  {"symbol": "XLC",   "description": "Communication Services SPDR ETF",  "type": "ETF"},
  {"symbol": "SMH",   "description": "VanEck Semiconductor ETF",         "type": "ETF"},
  {"symbol": "SOXX",  "description": "iShares Semiconductor ETF",        "type": "ETF"},
  {"symbol": "KWEB",  "description": "KraneShares CSI China Internet ETF","type": "ETF"},
  {"symbol": "HACK",  "description": "ETFMG Prime Cyber Security ETF",   "type": "ETF"},
  {"symbol": "CIBR",  "description": "First Trust Nasdaq Cybersecurity",  "type": "ETF"},
  {"symbol": "BOTZ",  "description": "Global X Robotics & AI ETF",       "type": "ETF"},
  {"symbol": "ROBO",  "description": "Robo Global Robotics & AI ETF",    "type": "ETF"},
  {"symbol": "JETS",  "description": "US Global Jets ETF",               "type": "ETF"},
  {"symbol": "ICLN",  "description": "iShares Global Clean Energy ETF",  "type": "ETF"},
  {"symbol": "TAN",   "description": "Invesco Solar ETF",                "type": "ETF"},
  {"symbol": "FAN",   "description": "First Trust Global Wind Energy",   "type": "ETF"},
  {"symbol": "EEM",   "description": "iShares MSCI Emerging Markets ETF","type": "ETF"},
  {"symbol": "EFA",   "description": "iShares MSCI EAFE ETF",            "type": "ETF"},
  {"symbol": "VEA",   "description": "Vanguard FTSE Developed Markets",  "type": "ETF"},
  {"symbol": "VWO",   "description": "Vanguard FTSE Emerging Markets",   "type": "ETF"},
  {"symbol": "EWJ",   "description": "iShares MSCI Japan ETF",           "type": "ETF"},
  {"symbol": "EWZ",   "description": "iShares MSCI Brazil ETF",          "type": "ETF"},
  {"symbol": "EWG",   "description": "iShares MSCI Germany ETF",         "type": "ETF"},
  {"symbol": "EWY",   "description": "iShares MSCI South Korea ETF",     "type": "ETF"},
  {"symbol": "EWT",   "description": "iShares MSCI Taiwan ETF",          "type": "ETF"},
  {"symbol": "INDA",  "description": "iShares MSCI India ETF",           "type": "ETF"},
  {"symbol": "GXC",   "description": "SPDR S&P China ETF",               "type": "ETF"},
  {"symbol": "VGK",   "description": "Vanguard FTSE Europe ETF",         "type": "ETF"},
  {"symbol": "IEMG",  "description": "iShares Core MSCI Emerging Mkts",  "type": "ETF"},
  {"symbol": "EWA",   "description": "iShares MSCI Australia ETF",       "type": "ETF"},
  {"symbol": "EWU",   "description": "iShares MSCI United Kingdom ETF",  "type": "ETF"},
  {"symbol": "TLT",   "description": "iShares 20+ Year Treasury Bond ETF","type": "ETF"},
  {"symbol": "IEF",   "description": "iShares 7-10 Year Treasury Bond",  "type": "ETF"},
  {"symbol": "SHY",   "description": "iShares 1-3 Year Treasury Bond",   "type": "ETF"},
  {"symbol": "AGG",   "description": "iShares Core US Aggregate Bond",   "type": "ETF"},
  {"symbol": "BND",   "description": "Vanguard Total Bond Market ETF",   "type": "ETF"},
  {"symbol": "LQD",   "description": "iShares iBoxx $ IG Corp Bond",     "type": "ETF"},
  {"symbol": "HYG",   "description": "iShares iBoxx $ High Yield Corp",  "type": "ETF"},
  {"symbol": "JNK",   "description": "SPDR Bloomberg High Yield Bond",   "type": "ETF"},
  {"symbol": "EMB",   "description": "iShares JP Morgan EM Bond ETF",    "type": "ETF"},
  {"symbol": "TIP",   "description": "iShares TIPS Bond ETF",            "type": "ETF"},
  {"symbol": "BNDX",  "description": "Vanguard Total Intl Bond ETF",     "type": "ETF"},
  {"symbol": "VCIT",  "description": "Vanguard Intermediate Corp Bond",  "type": "ETF"},
  {"symbol": "GLD",   "description": "SPDR Gold Shares ETF",             "type": "ETF"},
  {"symbol": "IAU",   "description": "iShares Gold Trust ETF",           "type": "ETF"},
  {"symbol": "SLV",   "description": "iShares Silver Trust ETF",         "type": "ETF"},
  {"symbol": "GDX",   "description": "VanEck Gold Miners ETF",           "type": "ETF"},
  {"symbol": "GDXJ",  "description": "VanEck Junior Gold Miners ETF",    "type": "ETF"},
  {"symbol": "USO",   "description": "United States Oil Fund ETF",       "type": "ETF"},
  {"symbol": "UNG",   "description": "United States Natural Gas Fund",   "type": "ETF"},
  {"symbol": "PDBC",  "description": "Invesco Optimum Yield Diversified","type": "ETF"},
  {"symbol": "UVXY",  "description": "ProShares Ultra VIX Short-Term ETF","type": "ETF"},
  {"symbol": "SVXY",  "description": "ProShares Short VIX Short-Term ETF","type": "ETF"},
  {"symbol": "VXX",   "description": "iPath Series B S&P 500 VIX ETN",   "type": "ETF"},
  {"symbol": "VIXY",  "description": "ProShares VIX Short-Term Futures", "type": "ETF"},
  {"symbol": "TQQQ",  "description": "ProShares UltraPro QQQ 3X",        "type": "ETF"},
  {"symbol": "SQQQ",  "description": "ProShares UltraPro Short QQQ 3X",  "type": "ETF"},
  {"symbol": "UPRO",  "description": "ProShares UltraPro S&P 500 3X",    "type": "ETF"},
  {"symbol": "SPXU",  "description": "ProShares UltraPro Short S&P 3X",  "type": "ETF"},
  {"symbol": "SPXL",  "description": "Direxion Daily S&P 500 Bull 3X",   "type": "ETF"},
  {"symbol": "SPXS",  "description": "Direxion Daily S&P 500 Bear 3X",   "type": "ETF"},
  {"symbol": "SOXL",  "description": "Direxion Daily Semis Bull 3X",     "type": "ETF"},
  {"symbol": "SOXS",  "description": "Direxion Daily Semis Bear 3X",     "type": "ETF"},
  {"symbol": "LABU",  "description": "Direxion Daily S&P Biotech Bull",  "type": "ETF"},
  {"symbol": "LABD",  "description": "Direxion Daily S&P Biotech Bear",  "type": "ETF"},
  {"symbol": "FNGU",  "description": "MicroSectors FANG+ Index 3X Bull", "type": "ETF"},
  {"symbol": "FNGD",  "description": "MicroSectors FANG+ Index 3X Bear", "type": "ETF"},
  {"symbol": "TECL",  "description": "Direxion Daily Tech Bull 3X",      "type": "ETF"},
  {"symbol": "TECS",  "description": "Direxion Daily Tech Bear 3X",      "type": "ETF"},
  {"symbol": "FAS",   "description": "Direxion Daily Financial Bull 3X", "type": "ETF"},
  {"symbol": "FAZ",   "description": "Direxion Daily Financial Bear 3X", "type": "ETF"},
  {"symbol": "ERX",   "description": "Direxion Daily Energy Bull 2X",    "type": "ETF"},
  {"symbol": "ERY",   "description": "Direxion Daily Energy Bear 2X",    "type": "ETF"},
  {"symbol": "NAIL",  "description": "Direxion Daily Homebuilders Bull",  "type": "ETF"},
  {"symbol": "ARKK",  "description": "ARK Innovation ETF",               "type": "ETF"},
  {"symbol": "ARKW",  "description": "ARK Next Generation Internet ETF", "type": "ETF"},
  {"symbol": "ARKG",  "description": "ARK Genomic Revolution ETF",       "type": "ETF"},
  {"symbol": "ARKF",  "description": "ARK Fintech Innovation ETF",       "type": "ETF"},
  {"symbol": "ARKQ",  "description": "ARK Autonomous Tech & Robotics",   "type": "ETF"},
  {"symbol": "WCLD",  "description": "WisdomTree Cloud Computing ETF",   "type": "ETF"},
  {"symbol": "BUG",   "description": "Global X Cybersecurity ETF",       "type": "ETF"},
  {"symbol": "SKYY",  "description": "First Trust Cloud Computing ETF",  "type": "ETF"},
  {"symbol": "CLOU",  "description": "Global X Cloud Computing ETF",     "type": "ETF"},
  {"symbol": "BLOK",  "description": "Amplify Transformational Data ETF","type": "ETF"},
  {"symbol": "BITO",  "description": "ProShares Bitcoin Strategy ETF",   "type": "ETF"},
  {"symbol": "GBTC",  "description": "Grayscale Bitcoin Trust",          "type": "ETF"},
  {"symbol": "IBIT",  "description": "iShares Bitcoin Trust ETF",        "type": "ETF"},
  {"symbol": "FBTC",  "description": "Fidelity Wise Origin Bitcoin ETF", "type": "ETF"},
  {"symbol": "KBWB",  "description": "Invesco KBW Bank ETF",             "type": "ETF"},
  {"symbol": "IAK",   "description": "iShares US Insurance ETF",         "type": "ETF"},
  {"symbol": "KRE",   "description": "SPDR S&P Regional Banking ETF",    "type": "ETF"},
  {"symbol": "KBE",   "description": "SPDR S&P Bank ETF",                "type": "ETF"},
  {"symbol": "IBB",   "description": "iShares Biotechnology ETF",        "type": "ETF"},
  {"symbol": "XBI",   "description": "SPDR S&P Biotech ETF",             "type": "ETF"},
  {"symbol": "ITB",   "description": "iShares US Home Construction ETF", "type": "ETF"},
  {"symbol": "XHB",   "description": "SPDR S&P Homebuilders ETF",        "type": "ETF"},
  {"symbol": "XRT",   "description": "SPDR S&P Retail ETF",              "type": "ETF"},
  {"symbol": "XME",   "description": "SPDR S&P Metals & Mining ETF",     "type": "ETF"},
  {"symbol": "XOP",   "description": "SPDR S&P Oil & Gas Explor. ETF",   "type": "ETF"},
  {"symbol": "OIH",   "description": "VanEck Oil Services ETF",          "type": "ETF"},
  {"symbol": "ES",    "description": "E-mini S&P 500 Futures",           "type": "Futures"},
  {"symbol": "MES",   "description": "Micro E-mini S&P 500 Futures",     "type": "Futures"},
  {"symbol": "NQ",    "description": "E-mini NASDAQ-100 Futures",        "type": "Futures"},
  {"symbol": "MNQ",   "description": "Micro E-mini NASDAQ-100 Futures",  "type": "Futures"},
  {"symbol": "RTY",   "description": "E-mini Russell 2000 Futures",      "type": "Futures"},
  {"symbol": "M2K",   "description": "Micro E-mini Russell 2000 Futures","type": "Futures"},
  {"symbol": "YM",    "description": "E-mini Dow Jones Futures",         "type": "Futures"},
  {"symbol": "MYM",   "description": "Micro E-mini Dow Jones Futures",   "type": "Futures"},
  {"symbol": "EMD",   "description": "E-mini S&P MidCap 400 Futures",    "type": "Futures"},
  {"symbol": "VX",    "description": "CBOE VIX Futures",                  "type": "Futures"},
  {"symbol": "6E",    "description": "Euro FX Futures",                  "type": "Futures"},
  {"symbol": "6B",    "description": "British Pound Futures",            "type": "Futures"},
  {"symbol": "6J",    "description": "Japanese Yen Futures",             "type": "Futures"},
  {"symbol": "6A",    "description": "Australian Dollar Futures",        "type": "Futures"},
  {"symbol": "6C",    "description": "Canadian Dollar Futures",          "type": "Futures"},
  {"symbol": "6S",    "description": "Swiss Franc Futures",              "type": "Futures"},
  {"symbol": "6N",    "description": "New Zealand Dollar Futures",       "type": "Futures"},
  {"symbol": "DX",    "description": "US Dollar Index Futures",          "type": "Futures"},
  {"symbol": "6M",    "description": "Mexican Peso Futures",             "type": "Futures"},
  {"symbol": "6Z",    "description": "South African Rand Futures",       "type": "Futures"},
  {"symbol": "CL",    "description": "Crude Oil WTI Futures",            "type": "Futures"},
  {"symbol": "MCL",   "description": "Micro WTI Crude Oil Futures",      "type": "Futures"},
  {"symbol": "NG",    "description": "Natural Gas Futures",              "type": "Futures"},
  {"symbol": "RB",    "description": "RBOB Gasoline Futures",            "type": "Futures"},
  {"symbol": "HO",    "description": "Heating Oil Futures",              "type": "Futures"},
  {"symbol": "QM",    "description": "E-mini Crude Oil Futures",         "type": "Futures"},
  {"symbol": "GC",    "description": "Gold Futures",                     "type": "Futures"},
  {"symbol": "MGC",   "description": "Micro Gold Futures",               "type": "Futures"},
  {"symbol": "SI",    "description": "Silver Futures",                   "type": "Futures"},
  {"symbol": "SIL",   "description": "E-mini Silver Futures",            "type": "Futures"},
  {"symbol": "HG",    "description": "Copper Futures",                   "type": "Futures"},
  {"symbol": "PL",    "description": "Platinum Futures",                 "type": "Futures"},
  {"symbol": "PA",    "description": "Palladium Futures",                "type": "Futures"},
  {"symbol": "ZC",    "description": "Corn Futures",                     "type": "Futures"},
  {"symbol": "ZS",    "description": "Soybean Futures",                  "type": "Futures"},
  {"symbol": "ZW",    "description": "Wheat Futures",                    "type": "Futures"},
  {"symbol": "ZL",    "description": "Soybean Oil Futures",              "type": "Futures"},
  {"symbol": "ZM",    "description": "Soybean Meal Futures",             "type": "Futures"},
  {"symbol": "KC",    "description": "Coffee Futures",                   "type": "Futures"},
  {"symbol": "CC",    "description": "Cocoa Futures",                    "type": "Futures"},
  {"symbol": "CT",    "description": "Cotton Futures",                   "type": "Futures"},
  {"symbol": "SB",    "description": "Sugar No. 11 Futures",             "type": "Futures"},
  {"symbol": "OJ",    "description": "Orange Juice Futures",             "type": "Futures"},
  {"symbol": "ZB",    "description": "30-Year T-Bond Futures",           "type": "Futures"},
  {"symbol": "UB",    "description": "Ultra T-Bond Futures",             "type": "Futures"},
  {"symbol": "ZN",    "description": "10-Year T-Note Futures",           "type": "Futures"},
  {"symbol": "ZF",    "description": "5-Year T-Note Futures",            "type": "Futures"},
  {"symbol": "ZT",    "description": "2-Year T-Note Futures",            "type": "Futures"},
  {"symbol": "ZQ",    "description": "30-Day Fed Funds Futures",         "type": "Futures"},
  {"symbol": "LE",    "description": "Live Cattle Futures",              "type": "Futures"},
  {"symbol": "HE",    "description": "Lean Hogs Futures",                "type": "Futures"},
  {"symbol": "GF",    "description": "Feeder Cattle Futures",            "type": "Futures"},
  {"symbol": "BTC",   "description": "Bitcoin CME Futures",              "type": "Futures"},
  {"symbol": "MBT",   "description": "Micro Bitcoin CME Futures",        "type": "Futures"},
  {"symbol": "ETH",   "description": "Ether CME Futures",                "type": "Futures"},
  {"symbol": "MET",   "description": "Micro Ether CME Futures",          "type": "Futures"},
  {"symbol": "AAPL",  "description": "Apple Inc.",                       "type": "Equity"},
  {"symbol": "MSFT",  "description": "Microsoft Corporation",            "type": "Equity"},
  {"symbol": "NVDA",  "description": "NVIDIA Corporation",               "type": "Equity"},
  {"symbol": "AMZN",  "description": "Amazon.com Inc.",                  "type": "Equity"},
  {"symbol": "GOOGL", "description": "Alphabet Inc. Class A",            "type": "Equity"},
  {"symbol": "GOOG",  "description": "Alphabet Inc. Class C",            "type": "Equity"},
  {"symbol": "META",  "description": "Meta Platforms Inc.",              "type": "Equity"},
  {"symbol": "TSLA",  "description": "Tesla Inc.",                       "type": "Equity"},
  {"symbol": "AVGO",  "description": "Broadcom Inc.",                    "type": "Equity"},
  {"symbol": "ORCL",  "description": "Oracle Corporation",               "type": "Equity"},
  {"symbol": "ADBE",  "description": "Adobe Inc.",                       "type": "Equity"},
  {"symbol": "CRM",   "description": "Salesforce Inc.",                  "type": "Equity"},
  {"symbol": "AMD",   "description": "Advanced Micro Devices Inc.",      "type": "Equity"},
  {"symbol": "INTC",  "description": "Intel Corporation",                "type": "Equity"},
  {"symbol": "QCOM",  "description": "Qualcomm Inc.",                    "type": "Equity"},
  {"symbol": "TXN",   "description": "Texas Instruments Inc.",           "type": "Equity"},
  {"symbol": "AMAT",  "description": "Applied Materials Inc.",           "type": "Equity"},
  {"symbol": "LRCX",  "description": "Lam Research Corporation",         "type": "Equity"},
  {"symbol": "KLAC",  "description": "KLA Corporation",                  "type": "Equity"},
  {"symbol": "MU",    "description": "Micron Technology Inc.",           "type": "Equity"},
  {"symbol": "MRVL",  "description": "Marvell Technology Inc.",          "type": "Equity"},
  {"symbol": "ASML",  "description": "ASML Holding N.V.",                "type": "Equity"},
  {"symbol": "TSM",   "description": "Taiwan Semiconductor (ADR)",       "type": "Equity"},
  {"symbol": "NFLX",  "description": "Netflix Inc.",                     "type": "Equity"},
  {"symbol": "SHOP",  "description": "Shopify Inc.",                     "type": "Equity"},
  {"symbol": "PLTR",  "description": "Palantir Technologies Inc.",       "type": "Equity"},
  {"symbol": "UBER",  "description": "Uber Technologies Inc.",           "type": "Equity"},
  {"symbol": "LYFT",  "description": "Lyft Inc.",                        "type": "Equity"},
  {"symbol": "ABNB",  "description": "Airbnb Inc.",                      "type": "Equity"},
  {"symbol": "DASH",  "description": "DoorDash Inc.",                    "type": "Equity"},
  {"symbol": "COIN",  "description": "Coinbase Global Inc.",             "type": "Equity"},
  {"symbol": "HOOD",  "description": "Robinhood Markets Inc.",           "type": "Equity"},
  {"symbol": "SOFI",  "description": "SoFi Technologies Inc.",           "type": "Equity"},
  {"symbol": "RBLX",  "description": "Roblox Corporation",               "type": "Equity"},
  {"symbol": "SPOT",  "description": "Spotify Technology S.A.",          "type": "Equity"},
  {"symbol": "PINS",  "description": "Pinterest Inc.",                   "type": "Equity"},
  {"symbol": "SNAP",  "description": "Snap Inc.",                        "type": "Equity"},
  {"symbol": "ZM",    "description": "Zoom Video Communications",        "type": "Equity"},
  {"symbol": "DOCU",  "description": "DocuSign Inc.",                    "type": "Equity"},
  {"symbol": "DDOG",  "description": "Datadog Inc.",                     "type": "Equity"},
  {"symbol": "CRWD",  "description": "CrowdStrike Holdings Inc.",        "type": "Equity"},
  {"symbol": "PANW",  "description": "Palo Alto Networks Inc.",          "type": "Equity"},
  {"symbol": "FTNT",  "description": "Fortinet Inc.",                    "type": "Equity"},
  {"symbol": "ZS",    "description": "Zscaler Inc.",                     "type": "Equity"},
  {"symbol": "OKTA",  "description": "Okta Inc.",                        "type": "Equity"},
  {"symbol": "NET",   "description": "Cloudflare Inc.",                  "type": "Equity"},
  {"symbol": "MDB",   "description": "MongoDB Inc.",                     "type": "Equity"},
  {"symbol": "TEAM",  "description": "Atlassian Corporation",            "type": "Equity"},
  {"symbol": "HUBS",  "description": "HubSpot Inc.",                     "type": "Equity"},
  {"symbol": "INTU",  "description": "Intuit Inc.",                      "type": "Equity"},
  {"symbol": "NOW",   "description": "ServiceNow Inc.",                  "type": "Equity"},
  {"symbol": "WDAY",  "description": "Workday Inc.",                     "type": "Equity"},
  {"symbol": "VEEV",  "description": "Veeva Systems Inc.",               "type": "Equity"},
  {"symbol": "PAYC",  "description": "Paycom Software Inc.",             "type": "Equity"},
  {"symbol": "BILL",  "description": "Bill.com Holdings Inc.",           "type": "Equity"},
  {"symbol": "TTD",   "description": "The Trade Desk Inc.",              "type": "Equity"},
  {"symbol": "ROKU",  "description": "Roku Inc.",                        "type": "Equity"},
  {"symbol": "TWLO",  "description": "Twilio Inc.",                      "type": "Equity"},
  {"symbol": "ESTC",  "description": "Elastic N.V.",                     "type": "Equity"},
  {"symbol": "GTLB",  "description": "GitLab Inc.",                      "type": "Equity"},
  {"symbol": "PATH",  "description": "UiPath Inc.",                      "type": "Equity"},
  {"symbol": "CFLT",  "description": "Confluent Inc.",                   "type": "Equity"},
  {"symbol": "S",     "description": "SentinelOne Inc.",                 "type": "Equity"},
  {"symbol": "SNOW",  "description": "Snowflake Inc.",                   "type": "Equity"},
  {"symbol": "MCHP",  "description": "Microchip Technology Inc.",        "type": "Equity"},
  {"symbol": "MPWR",  "description": "Monolithic Power Systems Inc.",    "type": "Equity"},
  {"symbol": "SWKS",  "description": "Skyworks Solutions Inc.",          "type": "Equity"},
  {"symbol": "QRVO",  "description": "Qorvo Inc.",                       "type": "Equity"},
  {"symbol": "WOLF",  "description": "Wolfspeed Inc.",                   "type": "Equity"},
  {"symbol": "ON",    "description": "ON Semiconductor Corporation",     "type": "Equity"},
  {"symbol": "ONTO",  "description": "Onto Innovation Inc.",             "type": "Equity"},
  {"symbol": "ACLS",  "description": "Axcelis Technologies Inc.",        "type": "Equity"},
  {"symbol": "ENTG",  "description": "Entegris Inc.",                    "type": "Equity"},
  {"symbol": "MSTR",  "description": "MicroStrategy Incorporated",       "type": "Equity"},
  {"symbol": "AFRM",  "description": "Affirm Holdings Inc.",             "type": "Equity"},
  {"symbol": "UPST",  "description": "Upstart Holdings Inc.",            "type": "Equity"},
  {"symbol": "SQ",    "description": "Block Inc. (Square)",              "type": "Equity"},
  {"symbol": "PYPL",  "description": "PayPal Holdings Inc.",             "type": "Equity"},
  {"symbol": "FI",    "description": "Fiserv Inc.",                      "type": "Equity"},
  {"symbol": "FIS",   "description": "Fidelity National Information",    "type": "Equity"},
  {"symbol": "GPN",   "description": "Global Payments Inc.",             "type": "Equity"},
  {"symbol": "TOST",  "description": "Toast Inc.",                       "type": "Equity"},
  {"symbol": "FOUR",  "description": "Shift4 Payments Inc.",             "type": "Equity"},
  {"symbol": "LLY",   "description": "Eli Lilly and Company",            "type": "Equity"},
  {"symbol": "UNH",   "description": "UnitedHealth Group Inc.",          "type": "Equity"},
  {"symbol": "JNJ",   "description": "Johnson & Johnson",                "type": "Equity"},
  {"symbol": "PFE",   "description": "Pfizer Inc.",                      "type": "Equity"},
  {"symbol": "MRK",   "description": "Merck & Co. Inc.",                 "type": "Equity"},
  {"symbol": "ABBV",  "description": "AbbVie Inc.",                      "type": "Equity"},
  {"symbol": "TMO",   "description": "Thermo Fisher Scientific Inc.",    "type": "Equity"},
  {"symbol": "ABT",   "description": "Abbott Laboratories",              "type": "Equity"},
  {"symbol": "BMY",   "description": "Bristol-Myers Squibb Company",     "type": "Equity"},
  {"symbol": "GILD",  "description": "Gilead Sciences Inc.",             "type": "Equity"},
  {"symbol": "AMGN",  "description": "Amgen Inc.",                       "type": "Equity"},
  {"symbol": "REGN",  "description": "Regeneron Pharmaceuticals",        "type": "Equity"},
  {"symbol": "BIIB",  "description": "Biogen Inc.",                      "type": "Equity"},
  {"symbol": "VRTX",  "description": "Vertex Pharmaceuticals",           "type": "Equity"},
  {"symbol": "MRNA",  "description": "Moderna Inc.",                     "type": "Equity"},
  {"symbol": "BNTX",  "description": "BioNTech SE (ADR)",                "type": "Equity"},
  {"symbol": "CVS",   "description": "CVS Health Corporation",           "type": "Equity"},
  {"symbol": "CI",    "description": "The Cigna Group",                  "type": "Equity"},
  {"symbol": "HUM",   "description": "Humana Inc.",                      "type": "Equity"},
  {"symbol": "ISRG",  "description": "Intuitive Surgical Inc.",          "type": "Equity"},
  {"symbol": "SYK",   "description": "Stryker Corporation",              "type": "Equity"},
  {"symbol": "MDT",   "description": "Medtronic PLC",                    "type": "Equity"},
  {"symbol": "BSX",   "description": "Boston Scientific Corporation",    "type": "Equity"},
  {"symbol": "EW",    "description": "Edwards Lifesciences Corp.",       "type": "Equity"},
  {"symbol": "DHR",   "description": "Danaher Corporation",              "type": "Equity"},
  {"symbol": "A",     "description": "Agilent Technologies Inc.",        "type": "Equity"},
  {"symbol": "IQV",   "description": "IQVIA Holdings Inc.",              "type": "Equity"},
  {"symbol": "ILMN",  "description": "Illumina Inc.",                    "type": "Equity"},
  {"symbol": "ZBH",   "description": "Zimmer Biomet Holdings",           "type": "Equity"},
  {"symbol": "BAX",   "description": "Baxter International Inc.",        "type": "Equity"},
  {"symbol": "BDX",   "description": "Becton Dickinson and Company",     "type": "Equity"},
  {"symbol": "DXCM",  "description": "DexCom Inc.",                      "type": "Equity"},
  {"symbol": "PODD",  "description": "Insulet Corporation",              "type": "Equity"},
  {"symbol": "IDXX",  "description": "IDEXX Laboratories Inc.",          "type": "Equity"},
  {"symbol": "MCK",   "description": "McKesson Corporation",             "type": "Equity"},
  {"symbol": "HCA",   "description": "HCA Healthcare Inc.",              "type": "Equity"},
  {"symbol": "GEHC",  "description": "GE HealthCare Technologies",       "type": "Equity"},
  {"symbol": "ALGN",  "description": "Align Technology Inc.",            "type": "Equity"},
  {"symbol": "ENPH",  "description": "Enphase Energy Inc.",              "type": "Equity"},
  {"symbol": "JPM",   "description": "JPMorgan Chase & Co.",             "type": "Equity"},
  {"symbol": "BAC",   "description": "Bank of America Corporation",      "type": "Equity"},
  {"symbol": "WFC",   "description": "Wells Fargo & Company",            "type": "Equity"},
  {"symbol": "C",     "description": "Citigroup Inc.",                   "type": "Equity"},
  {"symbol": "GS",    "description": "The Goldman Sachs Group Inc.",     "type": "Equity"},
  {"symbol": "MS",    "description": "Morgan Stanley",                   "type": "Equity"},
  {"symbol": "AXP",   "description": "American Express Company",         "type": "Equity"},
  {"symbol": "V",     "description": "Visa Inc.",                        "type": "Equity"},
  {"symbol": "MA",    "description": "Mastercard Incorporated",          "type": "Equity"},
  {"symbol": "BLK",   "description": "BlackRock Inc.",                   "type": "Equity"},
  {"symbol": "SCHW",  "description": "The Charles Schwab Corporation",   "type": "Equity"},
  {"symbol": "CME",   "description": "CME Group Inc.",                   "type": "Equity"},
  {"symbol": "ICE",   "description": "Intercontinental Exchange Inc.",   "type": "Equity"},
  {"symbol": "CBOE",  "description": "Cboe Global Markets Inc.",         "type": "Equity"},
  {"symbol": "SPGI",  "description": "S&P Global Inc.",                  "type": "Equity"},
  {"symbol": "MCO",   "description": "Moody's Corporation",              "type": "Equity"},
  {"symbol": "COF",   "description": "Capital One Financial Corp.",      "type": "Equity"},
  {"symbol": "DFS",   "description": "Discover Financial Services",      "type": "Equity"},
  {"symbol": "SYF",   "description": "Synchrony Financial",              "type": "Equity"},
  {"symbol": "AIG",   "description": "American International Group",     "type": "Equity"},
  {"symbol": "MET",   "description": "MetLife Inc.",                     "type": "Equity"},
  {"symbol": "PRU",   "description": "Prudential Financial Inc.",        "type": "Equity"},
  {"symbol": "AFL",   "description": "Aflac Incorporated",               "type": "Equity"},
  {"symbol": "TRV",   "description": "The Travelers Companies Inc.",     "type": "Equity"},
  {"symbol": "CB",    "description": "Chubb Limited",                    "type": "Equity"},
  {"symbol": "PGR",   "description": "The Progressive Corporation",      "type": "Equity"},
  {"symbol": "ALL",   "description": "The Allstate Corporation",         "type": "Equity"},
  {"symbol": "USB",   "description": "U.S. Bancorp",                     "type": "Equity"},
  {"symbol": "TFC",   "description": "Truist Financial Corporation",     "type": "Equity"},
  {"symbol": "PNC",   "description": "The PNC Financial Services Group", "type": "Equity"},
  {"symbol": "KEY",   "description": "KeyCorp",                          "type": "Equity"},
  {"symbol": "RF",    "description": "Regions Financial Corporation",    "type": "Equity"},
  {"symbol": "CFG",   "description": "Citizens Financial Group Inc.",    "type": "Equity"},
  {"symbol": "FITB",  "description": "Fifth Third Bancorp",              "type": "Equity"},
  {"symbol": "HBAN",  "description": "Huntington Bancshares Inc.",       "type": "Equity"},
  {"symbol": "HD",    "description": "The Home Depot Inc.",              "type": "Equity"},
  {"symbol": "LOW",   "description": "Lowe's Companies Inc.",            "type": "Equity"},
  {"symbol": "TGT",   "description": "Target Corporation",               "type": "Equity"},
  {"symbol": "WMT",   "description": "Walmart Inc.",                     "type": "Equity"},
  {"symbol": "COST",  "description": "Costco Wholesale Corporation",     "type": "Equity"},
  {"symbol": "DG",    "description": "Dollar General Corporation",       "type": "Equity"},
  {"symbol": "DLTR",  "description": "Dollar Tree Inc.",                 "type": "Equity"},
  {"symbol": "KO",    "description": "The Coca-Cola Company",            "type": "Equity"},
  {"symbol": "PEP",   "description": "PepsiCo Inc.",                     "type": "Equity"},
  {"symbol": "MCD",   "description": "McDonald's Corporation",           "type": "Equity"},
  {"symbol": "SBUX",  "description": "Starbucks Corporation",            "type": "Equity"},
  {"symbol": "YUM",   "description": "Yum! Brands Inc.",                 "type": "Equity"},
  {"symbol": "CMG",   "description": "Chipotle Mexican Grill Inc.",      "type": "Equity"},
  {"symbol": "DRI",   "description": "Darden Restaurants Inc.",          "type": "Equity"},
  {"symbol": "MO",    "description": "Altria Group Inc.",                "type": "Equity"},
  {"symbol": "PM",    "description": "Philip Morris International",      "type": "Equity"},
  {"symbol": "MDLZ",  "description": "Mondelez International Inc.",      "type": "Equity"},
  {"symbol": "KHC",   "description": "The Kraft Heinz Company",          "type": "Equity"},
  {"symbol": "GIS",   "description": "General Mills Inc.",               "type": "Equity"},
  {"symbol": "K",     "description": "Kellanova (Kellogg)",              "type": "Equity"},
  {"symbol": "TSN",   "description": "Tyson Foods Inc.",                 "type": "Equity"},
  {"symbol": "KR",    "description": "The Kroger Co.",                   "type": "Equity"},
  {"symbol": "BABA",  "description": "Alibaba Group Holding (ADR)",      "type": "Equity"},
  {"symbol": "JD",    "description": "JD.com Inc. (ADR)",                "type": "Equity"},
  {"symbol": "PDD",   "description": "PDD Holdings Inc. (Pinduoduo)",    "type": "Equity"},
  {"symbol": "BIDU",  "description": "Baidu Inc. (ADR)",                 "type": "Equity"},
  {"symbol": "NIO",   "description": "NIO Inc. (ADR)",                   "type": "Equity"},
  {"symbol": "XPEV",  "description": "XPeng Inc. (ADR)",                 "type": "Equity"},
  {"symbol": "LI",    "description": "Li Auto Inc. (ADR)",               "type": "Equity"},
  {"symbol": "MELI",  "description": "MercadoLibre Inc.",                "type": "Equity"},
  {"symbol": "SE",    "description": "Sea Limited (ADR)",                "type": "Equity"},
  {"symbol": "GRAB",  "description": "Grab Holdings Limited",            "type": "Equity"},
  {"symbol": "XOM",   "description": "Exxon Mobil Corporation",          "type": "Equity"},
  {"symbol": "CVX",   "description": "Chevron Corporation",              "type": "Equity"},
  {"symbol": "COP",   "description": "ConocoPhillips",                   "type": "Equity"},
  {"symbol": "OXY",   "description": "Occidental Petroleum Corp.",       "type": "Equity"},
  {"symbol": "SLB",   "description": "SLB (Schlumberger)",               "type": "Equity"},
  {"symbol": "HAL",   "description": "Halliburton Company",              "type": "Equity"},
  {"symbol": "BKR",   "description": "Baker Hughes Company",             "type": "Equity"},
  {"symbol": "MPC",   "description": "Marathon Petroleum Corporation",   "type": "Equity"},
  {"symbol": "VLO",   "description": "Valero Energy Corporation",        "type": "Equity"},
  {"symbol": "PSX",   "description": "Phillips 66",                      "type": "Equity"},
  {"symbol": "PXD",   "description": "Pioneer Natural Resources",        "type": "Equity"},
  {"symbol": "DVN",   "description": "Devon Energy Corporation",         "type": "Equity"},
  {"symbol": "EOG",   "description": "EOG Resources Inc.",               "type": "Equity"},
  {"symbol": "FANG",  "description": "Diamondback Energy Inc.",          "type": "Equity"},
  {"symbol": "APA",   "description": "APA Corporation",                  "type": "Equity"},
  {"symbol": "HES",   "description": "Hess Corporation",                 "type": "Equity"},
  {"symbol": "MRO",   "description": "Marathon Oil Corporation",         "type": "Equity"},
  {"symbol": "NEE",   "description": "NextEra Energy Inc.",              "type": "Equity"},
  {"symbol": "SO",    "description": "The Southern Company",             "type": "Equity"},
  {"symbol": "DUK",   "description": "Duke Energy Corporation",          "type": "Equity"},
  {"symbol": "EXC",   "description": "Exelon Corporation",               "type": "Equity"},
  {"symbol": "AEP",   "description": "American Electric Power Company",  "type": "Equity"},
  {"symbol": "PEG",   "description": "Public Service Enterprise Group",  "type": "Equity"},
  {"symbol": "ED",    "description": "Consolidated Edison Inc.",         "type": "Equity"},
  {"symbol": "AWK",   "description": "American Water Works Company",     "type": "Equity"},
  {"symbol": "BA",    "description": "The Boeing Company",               "type": "Equity"},
  {"symbol": "GE",    "description": "GE Aerospace",                     "type": "Equity"},
  {"symbol": "HON",   "description": "Honeywell International Inc.",     "type": "Equity"},
  {"symbol": "RTX",   "description": "RTX Corporation (Raytheon)",       "type": "Equity"},
  {"symbol": "LMT",   "description": "Lockheed Martin Corporation",      "type": "Equity"},
  {"symbol": "NOC",   "description": "Northrop Grumman Corporation",     "type": "Equity"},
  {"symbol": "GD",    "description": "General Dynamics Corporation",     "type": "Equity"},
  {"symbol": "LHX",   "description": "L3Harris Technologies Inc.",       "type": "Equity"},
  {"symbol": "TDG",   "description": "TransDigm Group Inc.",             "type": "Equity"},
  {"symbol": "CAT",   "description": "Caterpillar Inc.",                 "type": "Equity"},
  {"symbol": "DE",    "description": "Deere & Company",                  "type": "Equity"},
  {"symbol": "CMI",   "description": "Cummins Inc.",                     "type": "Equity"},
  {"symbol": "PCAR",  "description": "PACCAR Inc.",                      "type": "Equity"},
  {"symbol": "EMR",   "description": "Emerson Electric Co.",             "type": "Equity"},
  {"symbol": "ETN",   "description": "Eaton Corporation PLC",            "type": "Equity"},
  {"symbol": "PH",    "description": "Parker-Hannifin Corporation",      "type": "Equity"},
  {"symbol": "ITW",   "description": "Illinois Tool Works Inc.",         "type": "Equity"},
  {"symbol": "DOV",   "description": "Dover Corporation",                "type": "Equity"},
  {"symbol": "AME",   "description": "AMETEK Inc.",                      "type": "Equity"},
  {"symbol": "ROK",   "description": "Rockwell Automation Inc.",         "type": "Equity"},
  {"symbol": "XYL",   "description": "Xylem Inc.",                       "type": "Equity"},
  {"symbol": "WAT",   "description": "Waters Corporation",               "type": "Equity"},
  {"symbol": "IEX",   "description": "IDEX Corporation",                 "type": "Equity"},
  {"symbol": "ROP",   "description": "Roper Technologies Inc.",          "type": "Equity"},
  {"symbol": "ODFL",  "description": "Old Dominion Freight Line Inc.",   "type": "Equity"},
  {"symbol": "UNP",   "description": "Union Pacific Corporation",        "type": "Equity"},
  {"symbol": "CSX",   "description": "CSX Corporation",                  "type": "Equity"},
  {"symbol": "NSC",   "description": "Norfolk Southern Corporation",     "type": "Equity"},
  {"symbol": "CP",    "description": "Canadian Pacific Kansas City",     "type": "Equity"},
  {"symbol": "CNI",   "description": "Canadian National Railway (ADR)",  "type": "Equity"},
  {"symbol": "FDX",   "description": "FedEx Corporation",                "type": "Equity"},
  {"symbol": "UPS",   "description": "United Parcel Service Inc.",       "type": "Equity"},
  {"symbol": "GEV",   "description": "GE Vernova Inc.",                  "type": "Equity"},
  {"symbol": "F",     "description": "Ford Motor Company",               "type": "Equity"},
  {"symbol": "GM",    "description": "General Motors Company",           "type": "Equity"},
  {"symbol": "RIVN",  "description": "Rivian Automotive Inc.",           "type": "Equity"},
  {"symbol": "LCID",  "description": "Lucid Group Inc.",                 "type": "Equity"},
  {"symbol": "T",     "description": "AT&T Inc.",                        "type": "Equity"},
  {"symbol": "VZ",    "description": "Verizon Communications Inc.",      "type": "Equity"},
  {"symbol": "TMUS",  "description": "T-Mobile US Inc.",                 "type": "Equity"},
  {"symbol": "CHTR",  "description": "Charter Communications Inc.",      "type": "Equity"},
  {"symbol": "CMCSA", "description": "Comcast Corporation",              "type": "Equity"},
  {"symbol": "DIS",   "description": "The Walt Disney Company",          "type": "Equity"},
  {"symbol": "PARA",  "description": "Paramount Global",                 "type": "Equity"},
  {"symbol": "FOX",   "description": "Fox Corporation Class B",          "type": "Equity"},
  {"symbol": "FOXA",  "description": "Fox Corporation Class A",          "type": "Equity"},
  {"symbol": "OMC",   "description": "Omnicom Group Inc.",               "type": "Equity"},
  {"symbol": "IPG",   "description": "The Interpublic Group of Cos.",    "type": "Equity"},
  {"symbol": "AMT",   "description": "American Tower Corporation (REIT)","type": "Equity"},
  {"symbol": "PLD",   "description": "Prologis Inc. (REIT)",             "type": "Equity"},
  {"symbol": "CCI",   "description": "Crown Castle Inc. (REIT)",         "type": "Equity"},
  {"symbol": "EQIX",  "description": "Equinix Inc. (REIT)",              "type": "Equity"},
  {"symbol": "DLR",   "description": "Digital Realty Trust (REIT)",      "type": "Equity"},
  {"symbol": "PSA",   "description": "Public Storage (REIT)",            "type": "Equity"},
  {"symbol": "AVB",   "description": "AvalonBay Communities (REIT)",     "type": "Equity"},
  {"symbol": "EQR",   "description": "Equity Residential (REIT)",        "type": "Equity"},
  {"symbol": "VTR",   "description": "Ventas Inc. (REIT)",               "type": "Equity"},
  {"symbol": "WELL",  "description": "Welltower Inc. (REIT)",            "type": "Equity"},
  {"symbol": "O",     "description": "Realty Income Corporation (REIT)", "type": "Equity"},
  {"symbol": "VICI",  "description": "VICI Properties Inc. (REIT)",      "type": "Equity"},
  {"symbol": "MAA",   "description": "Mid-America Apartment (REIT)",     "type": "Equity"},
  {"symbol": "NNN",   "description": "NNN REIT Inc.",                    "type": "Equity"},
  {"symbol": "WPC",   "description": "W. P. Carey Inc. (REIT)",          "type": "Equity"},
  {"symbol": "SPG",   "description": "Simon Property Group (REIT)",      "type": "Equity"},
  {"symbol": "BXP",   "description": "Boston Properties Inc. (REIT)",    "type": "Equity"},
  {"symbol": "ARE",   "description": "Alexandria Real Estate (REIT)",    "type": "Equity"},
  {"symbol": "BRK",   "description": "Berkshire Hathaway (generic)",     "type": "Equity"},
  {"symbol": "NKE",   "description": "NIKE Inc.",                        "type": "Equity"},
  {"symbol": "TJX",   "description": "The TJX Companies Inc.",           "type": "Equity"},
  {"symbol": "ROST",  "description": "Ross Stores Inc.",                 "type": "Equity"},
  {"symbol": "MAR",   "description": "Marriott International Inc.",      "type": "Equity"},
  {"symbol": "HLT",   "description": "Hilton Worldwide Holdings Inc.",   "type": "Equity"},
  {"symbol": "H",     "description": "Hyatt Hotels Corporation",         "type": "Equity"},
  {"symbol": "WYNN",  "description": "Wynn Resorts Limited",             "type": "Equity"},
  {"symbol": "MGM",   "description": "MGM Resorts International",        "type": "Equity"},
  {"symbol": "LVS",   "description": "Las Vegas Sands Corp.",            "type": "Equity"},
  {"symbol": "CZR",   "description": "Caesars Entertainment Inc.",       "type": "Equity"},
  {"symbol": "DKNG",  "description": "DraftKings Inc.",                  "type": "Equity"},
  {"symbol": "AMC",   "description": "AMC Entertainment Holdings",       "type": "Equity"},
  {"symbol": "GME",   "description": "GameStop Corp.",                   "type": "Equity"},
  {"symbol": "BB",    "description": "BlackBerry Limited",               "type": "Equity"},
  {"symbol": "BBBY",  "description": "Bed Bath & Beyond (delisted)",     "type": "Equity"},
  {"symbol": "SPCE",  "description": "Virgin Galactic Holdings",         "type": "Equity"},
  {"symbol": "IONQ",  "description": "IonQ Inc.",                        "type": "Equity"},
  {"symbol": "RGTI",  "description": "Rigetti Computing Inc.",           "type": "Equity"},
  {"symbol": "QUBT",  "description": "Quantum Computing Inc.",           "type": "Equity"},
  {"symbol": "SMCI",  "description": "Super Micro Computer Inc.",        "type": "Equity"},
  {"symbol": "ARM",   "description": "Arm Holdings PLC (ADR)",           "type": "Equity"},
  {"symbol": "DELL",  "description": "Dell Technologies Inc.",           "type": "Equity"},
  {"symbol": "HPQ",   "description": "HP Inc.",                          "type": "Equity"},
  {"symbol": "HPE",   "description": "Hewlett Packard Enterprise",       "type": "Equity"},
  {"symbol": "IBM",   "description": "International Business Machines",  "type": "Equity"},
  {"symbol": "ACN",   "description": "Accenture PLC",                    "type": "Equity"},
  {"symbol": "CTSH",  "description": "Cognizant Technology Solutions",   "type": "Equity"},
  {"symbol": "WIT",   "description": "Wipro Limited (ADR)",              "type": "Equity"},
  {"symbol": "INFY",  "description": "Infosys Limited (ADR)",            "type": "Equity"},
  {"symbol": "SAP",   "description": "SAP SE (ADR)",                     "type": "Equity"},
  {"symbol": "NXPI",  "description": "NXP Semiconductors N.V.",          "type": "Equity"},
  {"symbol": "STX",   "description": "Seagate Technology Holdings",      "type": "Equity"},
  {"symbol": "WDC",   "description": "Western Digital Corporation",      "type": "Equity"},
  {"symbol": "NTAP",  "description": "NetApp Inc.",                      "type": "Equity"},
  {"symbol": "PSTG",  "description": "Pure Storage Inc.",                "type": "Equity"},
  {"symbol": "GDDY",  "description": "GoDaddy Inc.",                     "type": "Equity"},
  {"symbol": "ZI",    "description": "ZoomInfo Technologies Inc.",       "type": "Equity"},
  {"symbol": "AI",    "description": "C3.ai Inc.",                       "type": "Equity"},
  {"symbol": "BBAI",  "description": "BigBear.ai Holdings Inc.",         "type": "Equity"},
  {"symbol": "SOUN",  "description": "SoundHound AI Inc.",               "type": "Equity"},
  {"symbol": "OPEN",  "description": "Opendoor Technologies Inc.",       "type": "Equity"},
  {"symbol": "ZETA",  "description": "Zeta Global Holdings Corp.",       "type": "Equity"},
  {"symbol": "APP",   "description": "AppLovin Corporation",             "type": "Equity"},
  {"symbol": "CELH",  "description": "Celsius Holdings Inc.",            "type": "Equity"},
  {"symbol": "MNST",  "description": "Monster Beverage Corporation",     "type": "Equity"},
  {"symbol": "FIZZ",  "description": "National Beverage Corp.",          "type": "Equity"},
  {"symbol": "CVNA",  "description": "Carvana Co.",                      "type": "Equity"},
  {"symbol": "AN",    "description": "AutoNation Inc.",                  "type": "Equity"},
  {"symbol": "KMX",   "description": "CarMax Inc.",                      "type": "Equity"},
  {"symbol": "ORLY",  "description": "O'Reilly Automotive Inc.",         "type": "Equity"},
  {"symbol": "AZO",   "description": "AutoZone Inc.",                    "type": "Equity"},
  {"symbol": "TSCO",  "description": "Tractor Supply Company",           "type": "Equity"},
  {"symbol": "BBY",   "description": "Best Buy Co. Inc.",                "type": "Equity"},
  {"symbol": "M",     "description": "Macy's Inc.",                      "type": "Equity"},
  {"symbol": "EBAY",  "description": "eBay Inc.",                        "type": "Equity"},
  {"symbol": "ETSY",  "description": "Etsy Inc.",                        "type": "Equity"},
  {"symbol": "W",     "description": "Wayfair Inc.",                     "type": "Equity"},
  {"symbol": "Z",     "description": "Zillow Group Inc.",                "type": "Equity"},
  {"symbol": "RDFN",  "description": "Redfin Corporation",               "type": "Equity"},
  {"symbol": "EXPE",  "description": "Expedia Group Inc.",               "type": "Equity"},
  {"symbol": "BKNG",  "description": "Booking Holdings Inc.",            "type": "Equity"},
  {"symbol": "TRIP",  "description": "TripAdvisor Inc.",                 "type": "Equity"},
  {"symbol": "UAL",   "description": "United Airlines Holdings",         "type": "Equity"},
  {"symbol": "DAL",   "description": "Delta Air Lines Inc.",             "type": "Equity"},
  {"symbol": "AAL",   "description": "American Airlines Group Inc.",     "type": "Equity"},
  {"symbol": "LUV",   "description": "Southwest Airlines Co.",           "type": "Equity"},
  {"symbol": "ALK",   "description": "Alaska Air Group Inc.",            "type": "Equity"},
  {"symbol": "CCL",   "description": "Carnival Corporation",             "type": "Equity"},
  {"symbol": "RCL",   "description": "Royal Caribbean Group",            "type": "Equity"},
  {"symbol": "NCLH",  "description": "Norwegian Cruise Line Holdings",   "type": "Equity"},
  {"symbol": "HWM",   "description": "Howmet Aerospace Inc.",            "type": "Equity"},
  {"symbol": "TDY",   "description": "Teledyne Technologies Inc.",       "type": "Equity"},
  {"symbol": "HEI",   "description": "HEICO Corporation",                "type": "Equity"},
  {"symbol": "AXON",  "description": "Axon Enterprise Inc.",             "type": "Equity"},
  {"symbol": "TRMB",  "description": "Trimble Inc.",                     "type": "Equity"},
  {"symbol": "DHI",   "description": "D.R. Horton Inc.",                 "type": "Equity"},
  {"symbol": "LEN",   "description": "Lennar Corporation",               "type": "Equity"},
  {"symbol": "PHM",   "description": "PulteGroup Inc.",                  "type": "Equity"},
  {"symbol": "TOL",   "description": "Toll Brothers Inc.",               "type": "Equity"},
  {"symbol": "NVR",   "description": "NVR Inc.",                         "type": "Equity"},
  {"symbol": "BLDR",  "description": "Builders FirstSource Inc.",        "type": "Equity"},
  {"symbol": "VMC",   "description": "Vulcan Materials Company",         "type": "Equity"},
  {"symbol": "MLM",   "description": "Martin Marietta Materials",        "type": "Equity"},
  {"symbol": "FCX",   "description": "Freeport-McMoRan Inc.",            "type": "Equity"},
  {"symbol": "NEM",   "description": "Newmont Corporation",              "type": "Equity"},
  {"symbol": "AA",    "description": "Alcoa Corporation",                "type": "Equity"},
  {"symbol": "X",     "description": "United States Steel Corporation",  "type": "Equity"},
  {"symbol": "NUE",   "description": "Nucor Corporation",                "type": "Equity"},
  {"symbol": "STLD",  "description": "Steel Dynamics Inc.",              "type": "Equity"},
  {"symbol": "LIN",   "description": "Linde PLC",                        "type": "Equity"},
  {"symbol": "APD",   "description": "Air Products and Chemicals Inc.",  "type": "Equity"},
  {"symbol": "DD",    "description": "DuPont de Nemours Inc.",           "type": "Equity"},
  {"symbol": "DOW",   "description": "Dow Inc.",                         "type": "Equity"},
  {"symbol": "LYB",   "description": "LyondellBasell Industries N.V.",   "type": "Equity"},
  {"symbol": "PPG",   "description": "PPG Industries Inc.",              "type": "Equity"},
  {"symbol": "ECL",   "description": "Ecolab Inc.",                      "type": "Equity"},
  {"symbol": "SHW",   "description": "The Sherwin-Williams Company",     "type": "Equity"},
  {"symbol": "CTVA",  "description": "Corteva Inc.",                     "type": "Equity"},
  {"symbol": "FMC",   "description": "FMC Corporation",                  "type": "Equity"},
  {"symbol": "MOS",   "description": "The Mosaic Company",               "type": "Equity"},
  {"symbol": "CF",    "description": "CF Industries Holdings Inc.",      "type": "Equity"},
  {"symbol": "NTR",   "description": "Nutrien Ltd.",                     "type": "Equity"},
  {"symbol": "WLK",   "description": "Westlake Corporation",             "type": "Equity"},
  {"symbol": "RPM",   "description": "RPM International Inc.",           "type": "Equity"}
]
